python_optional/__init__.py
python_optional-1.1.0.dist-info/LICENSE.txt
python_optional-1.1.0.dist-info/METADATA
python_optional-1.1.0.dist-info/WHEEL
python_optional-1.1.0.dist-info/top_level.txt
python_optional-1.1.0.dist-info/RECORD
